[
  {
    "word": "lết bết",
    "definitions": [
      {
        "dict_name": "Từ điển Tiếng Việt thông dụng",
        "dict_definition": "[vật mang trên người] dài sát mặt đất và tựa như kéo lết khi di chuyển\nVí dụ:\n- quần dài lết bết"
      },
      {
        "dict_name": "Từ điển Tiếng Việt thông dụng",
        "dict_definition": "tỏ ra đuối sức, vận động, hoạt động rất khó khăn, chậm chạp\nVí dụ:\n- ốm lết bết \n - mệt quá, bước đi lết bết"
      },
      {
        "dict_name": "Từ điển Tiếng Việt - Hồ Ngọc Đức",
        "dict_definition": "@lết bết\n- Nói làm không nhanh chóng những công việc mình phải làm."
      },
      {
        "dict_name": "SPDict",
        "dict_definition": "@lết bết [lết bết]\n-languishing, slow moving, languid"
      },
      {
        "dict_name": "VNEDICT",
        "dict_definition": "languishing, slow moving, languid"
      }
    ]
  },
  {
    "word": "lếu",
    "definitions": [
      {
        "dict_name": "Từ điển Tiếng Việt - Hồ Ngọc Đức",
        "dict_definition": "@lếu\n- ph. Hỗn láo, xằng bậy: Chỉ nói lếu thôi."
      },
      {
        "dict_name": "SPDict",
        "dict_definition": "@lếu [lếu]\n-impolite, rude, unseemly, indecorous"
      },
      {
        "dict_name": "VNEDICT",
        "dict_definition": "impolite, rude, unseemly, indecorous"
      }
    ]
  },
  {
    "word": "lếch tha lếch thếch",
    "definitions": [
      {
        "dict_name": "Từ điển Tiếng Việt thông dụng",
        "dict_definition": "quá lếch thếch, trông rất tồi tàn, bệ rạc\nVí dụ:\n- ăn mặc lếch tha lếch thếch"
      },
      {
        "dict_name": "Từ điển Tiếng Việt - Hồ Ngọc Đức",
        "dict_definition": "@lếch tha lếch thếch\n- Nh. Lếch thếch."
      },
      {
        "dict_name": "SPDict",
        "dict_definition": "@lếch tha lếch thếch [lếch tha lếch thếch]\n-xem"
      }
    ]
  },
  {
    "word": "lếu láo",
    "definitions": [
      {
        "dict_name": "Từ điển Tiếng Việt thông dụng",
        "dict_definition": "láo, không kể gì đến khuôn phép [nói khái quát]\nVí dụ:\n- ăn nói lếu láo \n - thằng bé rất lếu láo!"
      },
      {
        "dict_name": "Từ điển Tiếng Việt thông dụng",
        "dict_definition": "[làm việc gì] qua loa cho xong, cho có\nVí dụ:\n- làm lếu láo cho xong việc \n - vẽ mấy nét lếu láo"
      },
      {
        "dict_name": "Từ điển Tiếng Việt - Hồ Ngọc Đức",
        "dict_definition": "@lếu láo\n- Thiếu lễ độ ; sai sự thật và thiếu lễ phép : Thái độ lếu láo ; Ăn nói lếu láo."
      },
      {
        "dict_name": "SPDict",
        "dict_definition": "@lếu láo\n*adj\n-untidy; slovenly\n=làm lếu láo\n+done in a slovenly way"
      },
      {
        "dict_name": "Việt Anh - Hồ Ngọc Đức",
        "dict_definition": "@lếu láo\n* adj\n- untidy; slovenly\n=làm lếu láo+done in a slovenly way"
      }
    ]
  },
  {
    "word": "lếch thếch",
    "definitions": [
      {
        "dict_name": "Từ điển Tiếng Việt thông dụng",
        "dict_definition": "lôi thôi, trông bệ rạc, khổ sở\nVí dụ:\n- quần áo lếch thếch \n - cả gia đình lếch thếch kéo nhau đi"
      },
      {
        "dict_name": "Từ điển Tiếng Việt - Hồ Ngọc Đức",
        "dict_definition": "@lếch thếch\n- Lôi thôi không gọn gàng: Ăn mặc lếch thếch; Lếch thếch một đàn con."
      },
      {
        "dict_name": "SPDict",
        "dict_definition": "@lếch thếch [lếch thếch]\n-slovenly;  untidy"
      },
      {
        "dict_name": "VNEDICT",
        "dict_definition": "messy, untidy"
      }
    ]
  },
  {
    "word": "lết",
    "definitions": [
      {
        "dict_name": "Từ điển Tiếng Việt thông dụng",
        "dict_definition": "di chuyển một cách khó khăn, chậm chạp bằng cách kéo lê chân hoặc phần dưới cơ thể trên mặt nền\nVí dụ:\n- tên lính đang lết vào đồn \n - con chó lết trên sân"
      },
      {
        "dict_name": "Từ điển Tiếng Việt - Hồ Ngọc Đức",
        "dict_definition": "@lết\n- đg. Kéo lê chân mà đi: Mệt mà cũng cố lết đến xem."
      },
      {
        "dict_name": "SPDict",
        "dict_definition": "@lết [lết]\n-be hardly able to drag one\"s legs along"
      },
      {
        "dict_name": "VNEDICT",
        "dict_definition": "to drag"
      }
    ]
  }
]