[
  {
    "word": "trở kháng phối hợp",
    "definitions": [
      {
        "dict_name": "SPDict",
        "dict_definition": "@Chuyên ngành kỹ thuật\n@Lĩnh vực: điện tử & viễn thông\n-matching impedance"
      }
    ]
  },
  {
    "word": "trở về liền",
    "definitions": [
      {
        "dict_name": "VNEDICT",
        "dict_definition": "to come right back, come back right away"
      }
    ]
  },
  {
    "word": "trở lại bình thường",
    "definitions": [
      {
        "dict_name": "VNEDICT",
        "dict_definition": "to return to normal"
      }
    ]
  },
  {
    "word": "trở lại",
    "definitions": [
      {
        "dict_name": "Từ điển Tiếng Việt thông dụng",
        "dict_definition": "quay về, quay lại nơi bắt đầu, nơi xuất phát\nVí dụ:\n- tôi trở lại quê nhà \n - trở lại lúc ban đầu"
      },
      {
        "dict_name": "Từ điển Tiếng Việt thông dụng",
        "dict_definition": "chuyển về trạng thái, tính chất [thường là tốt đẹp] ban đầu\nVí dụ:\n- không gian trở lại yên tĩnh \n - sức khoẻ đã trở lại bình thường"
      },
      {
        "dict_name": "Từ điển Tiếng Việt thông dụng",
        "dict_definition": "lấy đó làm mốc được coi là tối đa, không thể hơn\nVí dụ:\n- chỗ đó được mươi cân trở lại \n - chỉ mươi ngày trở lại là xong"
      },
      {
        "dict_name": "Từ điển Tiếng Việt - Hồ Ngọc Đức",
        "dict_definition": "@trở lại\n- đg. 1 Quay về, quay lại nơi bắt đầu, nơi xuất phát. Trở lại nơi cũ. Tác động trở lại. 2 Chuyển về trạng thái, tính chất (thường là tốt đẹp) ban đầu. Không gian trở lại yên tĩnh. Vui trở lại. Trở lại làm người lương thiện. 3 Lấy đó làm mốc tối đa, không thể hơn. Chừng hai mươi tuổi trở lại. Trăm cân trở lại."
      },
      {
        "dict_name": "SPDict",
        "dict_definition": "@trở lại\n*verb\n-to return, to come back (again)\n@Chuyên ngành kinh tế\n-return\n@Chuyên ngành kỹ thuật\n-reentrant\n-return\n-revert"
      },
      {
        "dict_name": "Việt Anh - Hồ Ngọc Đức",
        "dict_definition": "@trở lại\n* verb\n- to return, to come back (again)"
      },
      {
        "dict_name": "VNEDICT",
        "dict_definition": "to come back, return; again"
      }
    ]
  },
  {
    "word": "trở lại chính quyền",
    "definitions": [
      {
        "dict_name": "VNEDICT",
        "dict_definition": "to return to government"
      }
    ]
  },
  {
    "word": "trở cờ",
    "definitions": [
      {
        "dict_name": "VNEDICT",
        "dict_definition": "traitor, turncoat"
      }
    ]
  },
  {
    "word": "trở kháng đầu vào của anten",
    "definitions": [
      {
        "dict_name": "SPDict",
        "dict_definition": "@Chuyên ngành kỹ thuật\n@Lĩnh vực: điện tử & viễn thông\n-antenna input impedance"
      }
    ]
  },
  {
    "word": "trở nghề",
    "definitions": [
      {
        "dict_name": "Từ điển Tiếng Việt - Hồ Ngọc Đức",
        "dict_definition": "@trở nghề\n- đây là theo luyện nghề võ"
      }
    ]
  },
  {
    "word": "trở kháng khuếch tán",
    "definitions": [
      {
        "dict_name": "SPDict",
        "dict_definition": "@Chuyên ngành kỹ thuật\n@Lĩnh vực: điện lạnh\n-diffusion resistance"
      }
    ]
  },
  {
    "word": "trở lại luôn",
    "definitions": [
      {
        "dict_name": "SPDict",
        "dict_definition": "@Chuyên ngành kinh tế\n-recurrent\n-recurring"
      }
    ]
  },
  {
    "word": "trở kháng danh định",
    "definitions": [
      {
        "dict_name": "SPDict",
        "dict_definition": "@Chuyên ngành kỹ thuật\n@Lĩnh vực: điện\n-rated impedance"
      }
    ]
  },
  {
    "word": "trở kháng thứ tự thuận",
    "definitions": [
      {
        "dict_name": "SPDict",
        "dict_definition": "@Chuyên ngành kỹ thuật\n@Lĩnh vực: điện\n-positive-sequence output"
      }
    ]
  },
  {
    "word": "trở kháng của không khí đối với không khí",
    "definitions": [
      {
        "dict_name": "SPDict",
        "dict_definition": "@Chuyên ngành kỹ thuật\n@Lĩnh vực: xây dựng\n-air-to-air resistance"
      }
    ]
  },
  {
    "word": "trở vát",
    "definitions": [
      {
        "dict_name": "SPDict",
        "dict_definition": "@Chuyên ngành kỹ thuật\n@Lĩnh vực: giao thông & vận tải\n-go-about"
      }
    ]
  },
  {
    "word": "trở kháng đầu vào",
    "definitions": [
      {
        "dict_name": "SPDict",
        "dict_definition": "@Chuyên ngành kỹ thuật\n@Lĩnh vực: điện\n-input impedance"
      }
    ]
  },
  {
    "word": "trở kháng chuyển động điện tự do",
    "definitions": [
      {
        "dict_name": "SPDict",
        "dict_definition": "@Chuyên ngành kỹ thuật\n@Lĩnh vực: vật lý\n-free electrical motional impedance"
      }
    ]
  },
  {
    "word": "trở kháng ẩm",
    "definitions": [
      {
        "dict_name": "SPDict",
        "dict_definition": "@Chuyên ngành kỹ thuật\n@Lĩnh vực: điện lạnh\n-moisture resistance"
      }
    ]
  },
  {
    "word": "trở kháng kiểu thác",
    "definitions": [
      {
        "dict_name": "SPDict",
        "dict_definition": "@Chuyên ngành kỹ thuật\n@Lĩnh vực: toán & tin\n-avalanche impedance"
      }
    ]
  },
  {
    "word": "trở kháng sóng",
    "definitions": [
      {
        "dict_name": "SPDict",
        "dict_definition": "@Chuyên ngành kỹ thuật\n-intrinsic impedance\n-self-surge impedance\n-wave output"
      }
    ]
  },
  {
    "word": "trở kháng hiệu dụng",
    "definitions": [
      {
        "dict_name": "SPDict",
        "dict_definition": "@Chuyên ngành kỹ thuật\n@Lĩnh vực: điện lạnh\n-effective impedance"
      }
    ]
  },
  {
    "word": "trở kháng của sóng xung",
    "definitions": [
      {
        "dict_name": "SPDict",
        "dict_definition": "@Chuyên ngành kỹ thuật\n@Lĩnh vực: điện\n-surge impedance"
      }
    ]
  },
  {
    "word": "trở kháng đồng bộ",
    "definitions": [
      {
        "dict_name": "SPDict",
        "dict_definition": "@Chuyên ngành kỹ thuật\n@Lĩnh vực: điện\n-synchronous reactance"
      }
    ]
  },
  {
    "word": "trở thành một trở ngại",
    "definitions": [
      {
        "dict_name": "VNEDICT",
        "dict_definition": "to become an obstacle"
      }
    ]
  },
  {
    "word": "trở mũi",
    "definitions": [
      {
        "dict_name": "SPDict",
        "dict_definition": "@Chuyên ngành kỹ thuật\n@Lĩnh vực: giao thông & vận tải\n-cant"
      }
    ]
  },
  {
    "word": "trở thành khô",
    "definitions": [
      {
        "dict_name": "SPDict",
        "dict_definition": "@Chuyên ngành kỹ thuật\n@Lĩnh vực: y học\n-xerannis"
      }
    ]
  },
  {
    "word": "trở kháng đầu cuối",
    "definitions": [
      {
        "dict_name": "SPDict",
        "dict_definition": "@Chuyên ngành kỹ thuật\n@Lĩnh vực: điện\n-terminating impedance"
      }
    ]
  },
  {
    "word": "trở kháng sự cố",
    "definitions": [
      {
        "dict_name": "SPDict",
        "dict_definition": "@Chuyên ngành kỹ thuật\n@Lĩnh vực: điện\n-fault impedance"
      }
    ]
  },
  {
    "word": "trở kháng - điện dung/điện trở - tụ điện",
    "definitions": [
      {
        "dict_name": "SPDict",
        "dict_definition": "@Chuyên ngành kỹ thuật\n@Lĩnh vực: điện tử & viễn thông\n-Resistance - Capacitance/Resistor-Capacitor (RC)"
      }
    ]
  },
  {
    "word": "trở về đầu dòng tiếp theo",
    "definitions": [
      {
        "dict_name": "SPDict",
        "dict_definition": "@Chuyên ngành kỹ thuật\n@Lĩnh vực: toán & tin\n-carriage return line feed (CRLF)\n-CRLF (carriage return line feed)"
      }
    ]
  },
  {
    "word": "trở kháng tác dụng",
    "definitions": [
      {
        "dict_name": "SPDict",
        "dict_definition": "@Chuyên ngành kỹ thuật\n@Lĩnh vực: điện\n-active impedance"
      }
    ]
  },
  {
    "word": "trở kháng được ghép",
    "definitions": [
      {
        "dict_name": "SPDict",
        "dict_definition": "@Chuyên ngành kỹ thuật\n@Lĩnh vực: điện tử & viễn thông\n-coupled impedance"
      }
    ]
  },
  {
    "word": "trở thành thảm họa",
    "definitions": [
      {
        "dict_name": "VNEDICT",
        "dict_definition": "to become a disaster, tragedy"
      }
    ]
  },
  {
    "word": "trở kháng nghịch đảo",
    "definitions": [
      {
        "dict_name": "SPDict",
        "dict_definition": "@Chuyên ngành kỹ thuật\n@Lĩnh vực: điện lạnh\n-reciprocal impedance"
      }
    ]
  },
  {
    "word": "trở nên tốt hơn",
    "definitions": [
      {
        "dict_name": "SPDict",
        "dict_definition": "@Chuyên ngành kinh tế\n-look up"
      }
    ]
  },
  {
    "word": "trở trời",
    "definitions": [
      {
        "dict_name": "Từ điển Tiếng Việt thông dụng",
        "dict_definition": "thay đổi thời tiết, thường là xấu đi, về mặt gây ảnh hưởng đến sức khoẻ hoặc đời sống sinh hoạt\nVí dụ:\n- trở trời, người đau ê ẩm"
      },
      {
        "dict_name": "Từ điển Tiếng Việt - Hồ Ngọc Đức",
        "dict_definition": "@trở trời\n- X. Giở trời."
      },
      {
        "dict_name": "SPDict",
        "dict_definition": "@trở trời [trở trời]\n-xem"
      }
    ]
  },
  {
    "word": "trở kháng tự đột biến",
    "definitions": [
      {
        "dict_name": "SPDict",
        "dict_definition": "@Chuyên ngành kỹ thuật\n@Lĩnh vực: điện\n-self-surge impedance"
      }
    ]
  },
  {
    "word": "trở kháng đột biến tương hỗ",
    "definitions": [
      {
        "dict_name": "SPDict",
        "dict_definition": "@Chuyên ngành kỹ thuật\n@Lĩnh vực: điện\n-mutual surge impedance"
      }
    ]
  },
  {
    "word": "trở lại với",
    "definitions": [
      {
        "dict_name": "VNEDICT",
        "dict_definition": "returning to (what one was talking about)"
      }
    ]
  },
  {
    "word": "trở kháng anode",
    "definitions": [
      {
        "dict_name": "SPDict",
        "dict_definition": "@Chuyên ngành kỹ thuật\n@Lĩnh vực: toán & tin\n-anode impedance\n-plate impedance"
      }
    ]
  },
  {
    "word": "trở ẩm của chất cách nhiệt",
    "definitions": [
      {
        "dict_name": "SPDict",
        "dict_definition": "@Chuyên ngành kỹ thuật\n@Lĩnh vực: điện lạnh\n-insulation moisture resistance"
      }
    ]
  },
  {
    "word": "trở về an cư",
    "definitions": [
      {
        "dict_name": "VNEDICT",
        "dict_definition": "to return to a happy life"
      }
    ]
  },
  {
    "word": "trở về với thực tại",
    "definitions": [
      {
        "dict_name": "VNEDICT",
        "dict_definition": "to come back to reality"
      }
    ]
  },
  {
    "word": "trở gót",
    "definitions": [
      {
        "dict_name": "Từ điển Tiếng Việt - Hồ Ngọc Đức",
        "dict_definition": "@trở gót\n- Quay lại hướng cũ : Trở gót ra về."
      },
      {
        "dict_name": "SPDict",
        "dict_definition": "@trở gót\n*verb\n-to turn back, to retrace"
      },
      {
        "dict_name": "Việt Anh - Hồ Ngọc Đức",
        "dict_definition": "@trở gót\n* verb\n- to turn back, to retrace"
      },
      {
        "dict_name": "VNEDICT",
        "dict_definition": "to turn back, retrace"
      }
    ]
  },
  {
    "word": "trở kháng phức",
    "definitions": [
      {
        "dict_name": "SPDict",
        "dict_definition": "@Chuyên ngành kỹ thuật\n@Lĩnh vực: điện lạnh\n-electrical impedance"
      }
    ]
  },
  {
    "word": "trở kháng thứ tự không",
    "definitions": [
      {
        "dict_name": "SPDict",
        "dict_definition": "@Chuyên ngành kỹ thuật\n@Lĩnh vực: điện\n-zero-sequence output"
      },
      {
        "dict_name": "VNEDICT",
        "dict_definition": "zero phase sequence impedance"
      }
    ]
  },
  {
    "word": "trở lực bề mặt nước đá",
    "definitions": [
      {
        "dict_name": "SPDict",
        "dict_definition": "@Chuyên ngành kỹ thuật\n@Lĩnh vực: điện lạnh\n-ice surface resistance"
      }
    ]
  },
  {
    "word": "trở đi",
    "definitions": [
      {
        "dict_name": "Từ điển Tiếng Việt - Hồ Ngọc Đức",
        "dict_definition": "@trở đi\n- ph. Tính từ đó về sau: Từ nay trở đi."
      },
      {
        "dict_name": "SPDict",
        "dict_definition": "@trở đi [trở đi]\n-... and later;  downwards;  forwards;  onwards"
      },
      {
        "dict_name": "VNEDICT",
        "dict_definition": "~ and later, downwards, forwards, onwards"
      }
    ]
  },
  {
    "word": "trở nên ổn định, củng cố",
    "definitions": [
      {
        "dict_name": "SPDict",
        "dict_definition": "@Chuyên ngành kinh tế\n-steady"
      }
    ]
  },
  {
    "word": "trở thành hội viên",
    "definitions": [
      {
        "dict_name": "VNEDICT",
        "dict_definition": "to become a member"
      }
    ]
  },
  {
    "word": "trở lên",
    "definitions": [
      {
        "dict_name": "Từ điển Tiếng Việt - Hồ Ngọc Đức",
        "dict_definition": "@trở lên\n- Tính từ đó lên trên: Mười ngày trở lên."
      },
      {
        "dict_name": "SPDict",
        "dict_definition": "@trở lên [trở lên]\n-... and above/over\n-to go/come up again;  to go/come back up"
      },
      {
        "dict_name": "VNEDICT",
        "dict_definition": "and over, and above"
      }
    ]
  },
  {
    "word": "trở thành một đề tài lớn",
    "definitions": [
      {
        "dict_name": "VNEDICT",
        "dict_definition": "to become a large topic"
      }
    ]
  },
  {
    "word": "trở kháng của không gian tự do",
    "definitions": [
      {
        "dict_name": "SPDict",
        "dict_definition": "@Chuyên ngành kỹ thuật\n@Lĩnh vực: điện tử & viễn thông\n-impedance of free space"
      }
    ]
  },
  {
    "word": "trở xuống",
    "definitions": [
      {
        "dict_name": "Từ điển Tiếng Việt - Hồ Ngọc Đức",
        "dict_definition": "@trở xuống\n- Tính từ đó xuống : Từ cấp tỉnh trở xuống."
      },
      {
        "dict_name": "SPDict",
        "dict_definition": "@trở xuống\n*adv\n-downwards"
      },
      {
        "dict_name": "Việt Anh - Hồ Ngọc Đức",
        "dict_definition": "@trở xuống\n* adv\n- downwards"
      },
      {
        "dict_name": "VNEDICT",
        "dict_definition": "downwards"
      }
    ]
  },
  {
    "word": "trở kháng kế",
    "definitions": [
      {
        "dict_name": "SPDict",
        "dict_definition": "@Chuyên ngành kỹ thuật\n@Lĩnh vực: điện\n-Z-meter"
      }
    ]
  },
  {
    "word": "trở về của thông tin",
    "definitions": [
      {
        "dict_name": "SPDict",
        "dict_definition": "@Chuyên ngành kỹ thuật\n@Lĩnh vực: điện tử & viễn thông\n-auxiliary feedback channel"
      }
    ]
  },
  {
    "word": "trở kháng đèn",
    "definitions": [
      {
        "dict_name": "SPDict",
        "dict_definition": "@Chuyên ngành kỹ thuật\n@Lĩnh vực: điện tử & viễn thông\n-tube impedance"
      }
    ]
  },
  {
    "word": "trở thành không",
    "definitions": [
      {
        "dict_name": "SPDict",
        "dict_definition": "@Chuyên ngành kỹ thuật\n@Lĩnh vực: vật lý\n-become zero"
      }
    ]
  },
  {
    "word": "trở về qua đất",
    "definitions": [
      {
        "dict_name": "SPDict",
        "dict_definition": "@Chuyên ngành kỹ thuật\n@Lĩnh vực: điện lạnh\n-earth return"
      }
    ]
  },
  {
    "word": "trở kháng đường truyền",
    "definitions": [
      {
        "dict_name": "SPDict",
        "dict_definition": "@Chuyên ngành kỹ thuật\n@Lĩnh vực: toán & tin\n-line impedance\n@Lĩnh vực: điện lạnh\n-transmission-line impedance"
      }
    ]
  },
  {
    "word": "trở kháng rò rỉ",
    "definitions": [
      {
        "dict_name": "SPDict",
        "dict_definition": "@Chuyên ngành kỹ thuật\n@Lĩnh vực: điện lạnh\n-leak resistance"
      }
    ]
  },
  {
    "word": "trở kháng không gian tự do",
    "definitions": [
      {
        "dict_name": "SPDict",
        "dict_definition": "@Chuyên ngành kỹ thuật\n@Lĩnh vực: vật lý\n-impedance of free space"
      }
    ]
  },
  {
    "word": "trở nên xù xì",
    "definitions": [
      {
        "dict_name": "SPDict",
        "dict_definition": "@Chuyên ngành kỹ thuật\n@Lĩnh vực: ô tô\n-grain coarsening or grain growth"
      }
    ]
  },
  {
    "word": "trở kháng học",
    "definitions": [
      {
        "dict_name": "SPDict",
        "dict_definition": "@Chuyên ngành kỹ thuật\n@Lĩnh vực: toán & tin\n-mechanical impedance"
      }
    ]
  },
  {
    "word": "trở lại như trước (giá ca, việc kinh doanh)",
    "definitions": [
      {
        "dict_name": "SPDict",
        "dict_definition": "@Chuyên ngành kinh tế\n-recovery"
      }
    ]
  },
  {
    "word": "trở lại nguyên thể",
    "definitions": [
      {
        "dict_name": "SPDict",
        "dict_definition": "@Chuyên ngành kỹ thuật\n@Lĩnh vực: toán & tin\n-cut back\n-revert"
      }
    ]
  },
  {
    "word": "trở mặt",
    "definitions": [
      {
        "dict_name": "Từ điển Tiếng Việt thông dụng",
        "dict_definition": "đột nhiên đối xử ngược hẳn lại với sự tử tế trước đó\nVí dụ:\n- nó trở mặt với tôi \n - trở mặt nói xấu bạn"
      },
      {
        "dict_name": "Từ điển Tiếng Việt - Hồ Ngọc Đức",
        "dict_definition": "@trở mặt\n- đgt. Lật lọng, đang tử tế bỗng quay ngay ra có thái độ chống lại: trở mặt nói xấu bạn  trở mặt viết đơn tố cáo ban lãnh đạo."
      },
      {
        "dict_name": "SPDict",
        "dict_definition": "@trở mặt\n*verb\n-to change about"
      },
      {
        "dict_name": "Việt Anh - Hồ Ngọc Đức",
        "dict_definition": "@trở mặt\n* verb\n- to change about"
      },
      {
        "dict_name": "VNEDICT",
        "dict_definition": "to change about"
      }
    ]
  },
  {
    "word": "trở kháng thành phần của kháng trở nguồn",
    "definitions": [
      {
        "dict_name": "SPDict",
        "dict_definition": "@Chuyên ngành kỹ thuật\n@Lĩnh vực: điện tử & viễn thông\n-resistive component of an impedance\n-resistive component of the source impedance"
      }
    ]
  },
  {
    "word": "trở kháng riêng",
    "definitions": [
      {
        "dict_name": "SPDict",
        "dict_definition": "@Chuyên ngành kỹ thuật\n@Lĩnh vực: điện\n-characteristic impedance"
      }
    ]
  },
  {
    "word": "trở gió",
    "definitions": [
      {
        "dict_name": "Từ điển Tiếng Việt - Hồ Ngọc Đức",
        "dict_definition": "@trở gió\n- Nói gió đột nhiên đổi chiều hoặc thổi mạnh."
      },
      {
        "dict_name": "SPDict",
        "dict_definition": "@trở gió [trở gió]\n-the wind chages its direction"
      },
      {
        "dict_name": "VNEDICT",
        "dict_definition": "the wind changes its direction"
      }
    ]
  },
  {
    "word": "trở kháng bức xạ",
    "definitions": [
      {
        "dict_name": "SPDict",
        "dict_definition": "@Chuyên ngành kỹ thuật\n@Lĩnh vực: điện tử & viễn thông\n-radiation resistance"
      }
    ]
  },
  {
    "word": "trở",
    "definitions": [
      {
        "dict_name": "Từ điển Tiếng Việt thông dụng",
        "dict_definition": "tang\nVí dụ:\n- nhà có trở \n - để trở"
      },
      {
        "dict_name": "Từ điển Tiếng Việt thông dụng",
        "dict_definition": "đảo ngược vị trí, cho đầu thành đuôi, trên thành dưới và ngược lại\nVí dụ:\n- trở cá cho chín đều \n - trở người cho đỡ mỏi"
      },
      {
        "dict_name": "Từ điển Tiếng Việt thông dụng",
        "dict_definition": "quay ngược lại, đi về hướng hay vị trí ban đầu\nVí dụ:\n- anh ấy đã trở về quê cũ \n - kim đồng hồ trở về số 0."
      },
      {
        "dict_name": "Từ điển Tiếng Việt thông dụng",
        "dict_definition": "[diễn biến] chuyển sang chiều hướng khác, thường là xấu đi\nVí dụ:\n- trời trở gió \n - \"Hai em hỏi trước, han sau, Đứng trông, chàng cũng trở sầu làm tươi.\" (TKiều)"
      },
      {
        "dict_name": "Từ điển Tiếng Việt thông dụng",
        "dict_definition": "[từ cái mốc xác định] hướng về một phía nào đó để tính phạm vi thời gian, không gian, số lượng\nVí dụ:\n- từ Vinh trở ra \n - những năm 80 trở về trước"
      },
      {
        "dict_name": "Từ điển Tiếng Việt - Hồ Ngọc Đức",
        "dict_definition": "@trở\n- 1 dt. Tang: nhà có trở.\n- 2 đgt. 1. Đảo ngược vị trí đầu thành đuôi, trên thành dưới, trái thành phải: trở mặt vải  trở đầu đũa. 2. Quay ngược lại, đi về hướng hay vị trí ban đầu: trở về nhà  trở gót  ra sân lại trở vào nhà. 3. Quay, hướng về, phía nào đó: trở cửa về hướng đông. 4. Chuyển đổi sang chiều hướng nào, thường là xấu: trở bệnh  Trời trở gió. 5. Hướng đến phạm vi nào từ một giới hạn cụ thể: từ Nam Định trở ra  từ mười tám tuổi trở xuống."
      },
      {
        "dict_name": "SPDict",
        "dict_definition": "@trở\n*verb\n-to turn; to change\n@Chuyên ngành kỹ thuật\n@Lĩnh vực: cơ khí & công trình\n-chisel"
      },
      {
        "dict_name": "Việt Anh - Hồ Ngọc Đức",
        "dict_definition": "@trở\n* verb\n- to turn; to change"
      },
      {
        "dict_name": "VNEDICT",
        "dict_definition": "to return; to hamper, hinder; to turn, change"
      }
    ]
  },
  {
    "word": "trở kháng thứ tự nghịch",
    "definitions": [
      {
        "dict_name": "SPDict",
        "dict_definition": "@Chuyên ngành kỹ thuật\n@Lĩnh vực: điện\n-negative-sequence impedance"
      },
      {
        "dict_name": "VNEDICT",
        "dict_definition": "negative phase sequence impedence"
      }
    ]
  },
  {
    "word": "trở lực khi lăn",
    "definitions": [
      {
        "dict_name": "SPDict",
        "dict_definition": "@Chuyên ngành kỹ thuật\n@Lĩnh vực: cơ khí & công trình\n-rolling resistance"
      }
    ]
  },
  {
    "word": "trở kháng điểm truyền",
    "definitions": [
      {
        "dict_name": "SPDict",
        "dict_definition": "@Chuyên ngành kỹ thuật\n@Lĩnh vực: điện\n-driving-point impedance"
      }
    ]
  },
  {
    "word": "trở lại ngay",
    "definitions": [
      {
        "dict_name": "VNEDICT",
        "dict_definition": "to come right back"
      }
    ]
  },
  {
    "word": "trở kháng lớp",
    "definitions": [
      {
        "dict_name": "SPDict",
        "dict_definition": "@Chuyên ngành kỹ thuật\n@Lĩnh vực: toán & tin\n-layer impedance"
      }
    ]
  },
  {
    "word": "trở về với bạo lực",
    "definitions": [
      {
        "dict_name": "VNEDICT",
        "dict_definition": "to resort to force, violence"
      }
    ]
  },
  {
    "word": "trở ngại kỹ thuật",
    "definitions": [
      {
        "dict_name": "SPDict",
        "dict_definition": "@Chuyên ngành kinh tế\n-technical hitch"
      }
    ]
  },
  {
    "word": "trở về quy chiếu",
    "definitions": [
      {
        "dict_name": "SPDict",
        "dict_definition": "@Chuyên ngành kỹ thuật\n@Lĩnh vực: toán & tin\n-return to reference"
      }
    ]
  },
  {
    "word": "trở kháng được thích ứng",
    "definitions": [
      {
        "dict_name": "SPDict",
        "dict_definition": "@Chuyên ngành kỹ thuật\n@Lĩnh vực: điện\n-matched impedance"
      }
    ]
  },
  {
    "word": "trở về nước",
    "definitions": [
      {
        "dict_name": "SPDict",
        "dict_definition": "@Chuyên ngành kỹ thuật\n@Lĩnh vực: giao thông & vận tải\n-homeward-bound"
      }
    ]
  },
  {
    "word": "trở kháng cao",
    "definitions": [
      {
        "dict_name": "SPDict",
        "dict_definition": "@Chuyên ngành kỹ thuật\n@Lĩnh vực: điện tử & viễn thông\n-high impedance"
      }
    ]
  },
  {
    "word": "trở nên bão hòa",
    "definitions": [
      {
        "dict_name": "SPDict",
        "dict_definition": "@Chuyên ngành kỹ thuật\n@Lĩnh vực: toán & tin\n-to saturate"
      }
    ]
  },
  {
    "word": "trở nên có hiệu lực",
    "definitions": [
      {
        "dict_name": "SPDict",
        "dict_definition": "@Chuyên ngành kỹ thuật\n@Lĩnh vực: toán & tin\n-to be become active\n-to take effect"
      }
    ]
  },
  {
    "word": "trở kháng điểm rẽ",
    "definitions": [
      {
        "dict_name": "SPDict",
        "dict_definition": "@Chuyên ngành kỹ thuật\n@Lĩnh vực: toán & tin\n-turn impedance"
      }
    ]
  },
  {
    "word": "trở kháng âm thanh",
    "definitions": [
      {
        "dict_name": "SPDict",
        "dict_definition": "@Chuyên ngành kỹ thuật\n@Lĩnh vực: toán & tin\n-acoustic reactance"
      }
    ]
  },
  {
    "word": "trở quẻ",
    "definitions": [
      {
        "dict_name": "Từ điển Tiếng Việt - Hồ Ngọc Đức",
        "dict_definition": "@trở quẻ\n- X. Giở quẻ."
      },
      {
        "dict_name": "SPDict",
        "dict_definition": "@trở quẻ [trở quẻ]\n-to change one\"s tactics"
      },
      {
        "dict_name": "VNEDICT",
        "dict_definition": "to change one’s tactics"
      }
    ]
  },
  {
    "word": "trở nên bầu dục",
    "definitions": [
      {
        "dict_name": "SPDict",
        "dict_definition": "@Chuyên ngành kỹ thuật\n@Lĩnh vực: cơ khí & công trình\n-ovalize"
      }
    ]
  },
  {
    "word": "trở lực bề mặt",
    "definitions": [
      {
        "dict_name": "SPDict",
        "dict_definition": "@Chuyên ngành kỹ thuật\n@Lĩnh vực: điện lạnh\n-surface resistance"
      }
    ]
  },
  {
    "word": "trở kháng ngắn mạch",
    "definitions": [
      {
        "dict_name": "SPDict",
        "dict_definition": "@Chuyên ngành kỹ thuật\n@Lĩnh vực: điện\n-short-circuit output"
      }
    ]
  },
  {
    "word": "trở kháng bị chặn",
    "definitions": [
      {
        "dict_name": "SPDict",
        "dict_definition": "@Chuyên ngành kỹ thuật\n-blocked electrical impedance\n-blocked impedance\n-open circuit impedance"
      }
    ]
  },
  {
    "word": "trở kháng đặc trưng",
    "definitions": [
      {
        "dict_name": "SPDict",
        "dict_definition": "@Chuyên ngành kỹ thuật\n-characteristic admittance\n-intrinsic impedance\n-self-surge impedance"
      }
    ]
  },
  {
    "word": "trở về nhà",
    "definitions": [
      {
        "dict_name": "SPDict",
        "dict_definition": "@Chuyên ngành kỹ thuật\n@Lĩnh vực: giao thông & vận tải\n-homeward"
      },
      {
        "dict_name": "VNEDICT",
        "dict_definition": "to go home, return home"
      }
    ]
  },
  {
    "word": "trở kháng vào mạng điện",
    "definitions": [
      {
        "dict_name": "SPDict",
        "dict_definition": "@Chuyên ngành kỹ thuật\n@Lĩnh vực: điện lạnh\n-network input impedance"
      }
    ]
  },
  {
    "word": "trở kháng chu kỳ",
    "definitions": [
      {
        "dict_name": "SPDict",
        "dict_definition": "@Chuyên ngành kỹ thuật\n@Lĩnh vực: điện lạnh\n-cyclic impedance"
      }
    ]
  },
  {
    "word": "trở lại liền",
    "definitions": [
      {
        "dict_name": "VNEDICT",
        "dict_definition": "to come right back"
      }
    ]
  },
  {
    "word": "trở kháng làm thích ứng",
    "definitions": [
      {
        "dict_name": "SPDict",
        "dict_definition": "@Chuyên ngành kỹ thuật\n@Lĩnh vực: điện lạnh\n-matching impedance"
      }
    ]
  },
  {
    "word": "trở lại chính trị",
    "definitions": [
      {
        "dict_name": "VNEDICT",
        "dict_definition": "to return to politics"
      }
    ]
  },
  {
    "word": "trở lại chuyện của mày",
    "definitions": [
      {
        "dict_name": "VNEDICT",
        "dict_definition": "getting back to you"
      }
    ]
  },
  {
    "word": "trở kháng điện động",
    "definitions": [
      {
        "dict_name": "SPDict",
        "dict_definition": "@Chuyên ngành kỹ thuật\n@Lĩnh vực: vật lý\n-electrical motional impedance"
      }
    ]
  },
  {
    "word": "trở lực của dòng chảy",
    "definitions": [
      {
        "dict_name": "SPDict",
        "dict_definition": "@Chuyên ngành kỹ thuật\n@Lĩnh vực: điện lạnh\n-flow resistance"
      }
    ]
  },
  {
    "word": "trở kháng potier",
    "definitions": [
      {
        "dict_name": "SPDict",
        "dict_definition": "@Chuyên ngành kỹ thuật\n@Lĩnh vực: điện\n-Potier reactance"
      }
    ]
  },
  {
    "word": "trở giọng",
    "definitions": [
      {
        "dict_name": "Từ điển Tiếng Việt - Hồ Ngọc Đức",
        "dict_definition": "@trở giọng\n- X. Giở giọng."
      },
      {
        "dict_name": "SPDict",
        "dict_definition": "@trở giọng\n*verb\n-to change tune"
      },
      {
        "dict_name": "Việt Anh - Hồ Ngọc Đức",
        "dict_definition": "@trở giọng\n* verb\n- to change tune"
      },
      {
        "dict_name": "VNEDICT",
        "dict_definition": "to change tune"
      }
    ]
  },
  {
    "word": "trở kháng tập trung",
    "definitions": [
      {
        "dict_name": "SPDict",
        "dict_definition": "@Chuyên ngành kỹ thuật\n@Lĩnh vực: điện lạnh\n-lumped impedance"
      }
    ]
  },
  {
    "word": "trở mình",
    "definitions": [
      {
        "dict_name": "Từ điển Tiếng Việt thông dụng",
        "dict_definition": "xoay người để đổi thế nằm\nVí dụ:\n- ông ấy luôn trở mình \n - thằng bé vừa trở mình"
      },
      {
        "dict_name": "Từ điển Tiếng Việt - Hồ Ngọc Đức",
        "dict_definition": "@trở mình\n- Lật sang một phía khác khi đang nằm: Mệt quá không trở mình được."
      },
      {
        "dict_name": "SPDict",
        "dict_definition": "@trở mình [trở mình]\n-to turn over"
      },
      {
        "dict_name": "VNEDICT",
        "dict_definition": "to turn over"
      }
    ]
  },
  {
    "word": "trở dạ",
    "definitions": [
      {
        "dict_name": "Từ điển Tiếng Việt thông dụng",
        "dict_definition": "như chuyển dạ\nVí dụ:\n- chị ấy đang trở dạ"
      },
      {
        "dict_name": "Từ điển Tiếng Việt - Hồ Ngọc Đức",
        "dict_definition": "@trở dạ\n- X. Giở dạ đẻ."
      }
    ]
  },
  {
    "word": "trở về đất mẹ",
    "definitions": [
      {
        "dict_name": "VNEDICT",
        "dict_definition": "to return to one’s homeland"
      }
    ]
  },
  {
    "word": "trở kháng ghép",
    "definitions": [
      {
        "dict_name": "SPDict",
        "dict_definition": "@Chuyên ngành kỹ thuật\n@Lĩnh vực: điện\n-coupling impedance"
      }
    ]
  },
  {
    "word": "trở về quê hương",
    "definitions": [
      {
        "dict_name": "VNEDICT",
        "dict_definition": "to return to one’s homeland"
      }
    ]
  },
  {
    "word": "trở kháng chặn",
    "definitions": [
      {
        "dict_name": "SPDict",
        "dict_definition": "@Chuyên ngành kỹ thuật\n@Lĩnh vực: điện lạnh\n-blocked impedance"
      }
    ]
  },
  {
    "word": "trở kháng nguội",
    "definitions": [
      {
        "dict_name": "SPDict",
        "dict_definition": "@Chuyên ngành kỹ thuật\n@Lĩnh vực: điện tử & viễn thông\n-cold impedance"
      }
    ]
  },
  {
    "word": "trở quẻ (quan điểm, thái độ)",
    "definitions": [
      {
        "dict_name": "SPDict",
        "dict_definition": "@Chuyên ngành kinh tế\n-turnround"
      }
    ]
  },
  {
    "word": "trở sáng góc mở",
    "definitions": [
      {
        "dict_name": "SPDict",
        "dict_definition": "@Chuyên ngành kỹ thuật\n@Lĩnh vực: điện tử & viễn thông\n-aperture impedance"
      }
    ]
  },
  {
    "word": "trở kháng chùm tia",
    "definitions": [
      {
        "dict_name": "SPDict",
        "dict_definition": "@Chuyên ngành kỹ thuật\n@Lĩnh vực: toán & tin\n-beam impedance"
      }
    ]
  },
  {
    "word": "trở kháng chùm",
    "definitions": [
      {
        "dict_name": "SPDict",
        "dict_definition": "@Chuyên ngành kỹ thuật\n@Lĩnh vực: điện tử & viễn thông\n-beam impedance"
      }
    ]
  },
  {
    "word": "trở lại mặt biển (tàu ngầm)",
    "definitions": [
      {
        "dict_name": "SPDict",
        "dict_definition": "@Chuyên ngành kỹ thuật\n@Lĩnh vực: giao thông & vận tải\n-return to surface"
      }
    ]
  },
  {
    "word": "trở buồm",
    "definitions": [
      {
        "dict_name": "SPDict",
        "dict_definition": "@Chuyên ngành kỹ thuật\n-go-about\n-make a tack\n-tack"
      }
    ]
  },
  {
    "word": "trở lại làm việc",
    "definitions": [
      {
        "dict_name": "VNEDICT",
        "dict_definition": "to return to work"
      }
    ]
  },
  {
    "word": "trở kháng đầu ra",
    "definitions": [
      {
        "dict_name": "SPDict",
        "dict_definition": "@Chuyên ngành kỹ thuật\n@Lĩnh vực: điện\n-output"
      }
    ]
  },
  {
    "word": "trở nên cứng",
    "definitions": [
      {
        "dict_name": "SPDict",
        "dict_definition": "@Chuyên ngành kỹ thuật\n@Lĩnh vực: ô tô\n-solidify"
      }
    ]
  },
  {
    "word": "trở kháng sóng hỗ cảm",
    "definitions": [
      {
        "dict_name": "SPDict",
        "dict_definition": "@Chuyên ngành kỹ thuật\n@Lĩnh vực: điện lạnh\n-mutual surge impedance"
      }
    ]
  },
  {
    "word": "trở kháng",
    "definitions": [
      {
        "dict_name": "SPDict",
        "dict_definition": "@trở kháng [trở kháng]\n-impedance\n@Chuyên ngành kỹ thuật\n@Lĩnh vực: điện tử & viễn thông\n-impedance transformation\n@Lĩnh vực: xây dựng\n-impede"
      },
      {
        "dict_name": "VNEDICT",
        "dict_definition": "impedance"
      }
    ]
  },
  {
    "word": "trở kháng thấp",
    "definitions": [
      {
        "dict_name": "SPDict",
        "dict_definition": "@Chuyên ngành kỹ thuật\n@Lĩnh vực: điện tử & viễn thông\n-low impedance"
      }
    ]
  },
  {
    "word": "trở thành công cộng",
    "definitions": [
      {
        "dict_name": "SPDict",
        "dict_definition": "@Chuyên ngành kinh tế\n-going public"
      }
    ]
  },
  {
    "word": "trở kháng đánh thủng",
    "definitions": [
      {
        "dict_name": "SPDict",
        "dict_definition": "@Chuyên ngành kỹ thuật\n@Lĩnh vực: toán & tin\n-breakdown impedance"
      }
    ]
  },
  {
    "word": "trở xe tải",
    "definitions": [
      {
        "dict_name": "SPDict",
        "dict_definition": "@Chuyên ngành kinh tế\n-cartage"
      }
    ]
  },
  {
    "word": "trở nên sệt",
    "definitions": [
      {
        "dict_name": "SPDict",
        "dict_definition": "@Chuyên ngành kỹ thuật\n@Lĩnh vực: ô tô\n-gel"
      }
    ]
  },
  {
    "word": "trở kháng đầu phát",
    "definitions": [
      {
        "dict_name": "SPDict",
        "dict_definition": "@Chuyên ngành kỹ thuật\n@Lĩnh vực: điện lạnh\n-sending-end impedance"
      }
    ]
  },
  {
    "word": "trở kháng (điện)",
    "definitions": [
      {
        "dict_name": "SPDict",
        "dict_definition": "@Chuyên ngành kỹ thuật\n@Lĩnh vực: điện lạnh\n-electrical impedance"
      }
    ]
  },
  {
    "word": "trở kháng cực nguồn",
    "definitions": [
      {
        "dict_name": "SPDict",
        "dict_definition": "@Chuyên ngành kỹ thuật\n@Lĩnh vực: điện\n-source impedance"
      }
    ]
  },
  {
    "word": "trở kháng đột biến",
    "definitions": [
      {
        "dict_name": "SPDict",
        "dict_definition": "@Chuyên ngành kỹ thuật\n@Lĩnh vực: điện\n-surge-impedance"
      }
    ]
  },
  {
    "word": "trở cơ học",
    "definitions": [
      {
        "dict_name": "SPDict",
        "dict_definition": "@Chuyên ngành kỹ thuật\n@Lĩnh vực: vật lý\n-mechanical resistance"
      }
    ]
  },
  {
    "word": "trở kháng sóng (xung)",
    "definitions": [
      {
        "dict_name": "SPDict",
        "dict_definition": "@Chuyên ngành kỹ thuật\n@Lĩnh vực: điện\n-surge output"
      }
    ]
  },
  {
    "word": "trở kháng truyền đạt",
    "definitions": [
      {
        "dict_name": "SPDict",
        "dict_definition": "@Chuyên ngành kỹ thuật\n@Lĩnh vực: giao thông & vận tải\n-transfer impedance"
      }
    ]
  },
  {
    "word": "trở kháng tải",
    "definitions": [
      {
        "dict_name": "SPDict",
        "dict_definition": "@Chuyên ngành kỹ thuật\n@Lĩnh vực: cơ khí & công trình\n-load resistance"
      }
    ]
  },
  {
    "word": "trở lực",
    "definitions": [
      {
        "dict_name": "Từ điển Tiếng Việt thông dụng",
        "dict_definition": "cái gây ra sức cản trở lớn\nVí dụ:\n- gặp trở lực lớn"
      },
      {
        "dict_name": "Từ điển Tiếng Việt - Hồ Ngọc Đức",
        "dict_definition": "@trở lực\n- Nguyên nhân ngăn cản: Gặp nhiều trở lực trong công tác."
      },
      {
        "dict_name": "SPDict",
        "dict_definition": "@trở lực [trở lực]\n-hindrance;  obstacle;  impediment;  deterrent\n@Chuyên ngành kinh tế\n-barrier\n@Chuyên ngành kỹ thuật\n@Lĩnh vực: toán & tin\n-drag\n@Lĩnh vực: xây dựng\n-hindrance"
      },
      {
        "dict_name": "VNEDICT",
        "dict_definition": "hindrance, obstacle, impediment, deterrent"
      }
    ]
  },
  {
    "word": "trở lực lắc",
    "definitions": [
      {
        "dict_name": "SPDict",
        "dict_definition": "@Chuyên ngành kỹ thuật\n@Lĩnh vực: hóa học & vật liệu\n-rolling resistance"
      }
    ]
  },
  {
    "word": "trở kháng bên trong",
    "definitions": [
      {
        "dict_name": "SPDict",
        "dict_definition": "@Chuyên ngành kỹ thuật\n@Lĩnh vực: điện tử & viễn thông\n-internal impedance"
      }
    ]
  },
  {
    "word": "trở nên",
    "definitions": [
      {
        "dict_name": "Từ điển Tiếng Việt thông dụng",
        "dict_definition": "chuyển sang trạng thái khác\nVí dụ:\n- hiện tại công việc của tôi trở nên thuận lợi \n - tay chân trở nên luống cuống"
      },
      {
        "dict_name": "Từ điển Tiếng Việt thông dụng",
        "dict_definition": "như trở thành\nVí dụ:\n- trở nên giàu có \n - ông ta trở nên một doanh nhân nổi tiếng"
      },
      {
        "dict_name": "Từ điển Tiếng Việt - Hồ Ngọc Đức",
        "dict_definition": "@trở nên\n- Cg. Trở  thành. Hóa ra, thành ra : Trở nên hùng mạnh."
      },
      {
        "dict_name": "SPDict",
        "dict_definition": "@trở nên\n*verb\n-to turn, to become"
      },
      {
        "dict_name": "Việt Anh - Hồ Ngọc Đức",
        "dict_definition": "@trở nên\n* verb\n- to turn, to become"
      },
      {
        "dict_name": "VNEDICT",
        "dict_definition": "to turn, become"
      }
    ]
  },
  {
    "word": "trở kháng đông lạnh",
    "definitions": [
      {
        "dict_name": "SPDict",
        "dict_definition": "@Chuyên ngành kỹ thuật\n@Lĩnh vực: điện lạnh\n-freezing resistance"
      }
    ]
  },
  {
    "word": "trở đậu quân cơ",
    "definitions": [
      {
        "dict_name": "Từ điển Tiếng Việt - Hồ Ngọc Đức",
        "dict_definition": "@trở đậu quân cơ\n- làm ngăn trở chậm trễ việc quân. Nhắc việc Bá Cao can vua đừng đánh Phiên"
      }
    ]
  },
  {
    "word": "trở kháng ảo",
    "definitions": [
      {
        "dict_name": "SPDict",
        "dict_definition": "@Chuyên ngành kỹ thuật\n@Lĩnh vực: điện tử & viễn thông\n-virtual impedance"
      }
    ]
  },
  {
    "word": "trở kháng truyền đạt cơ học",
    "definitions": [
      {
        "dict_name": "SPDict",
        "dict_definition": "@Chuyên ngành kỹ thuật\n@Lĩnh vực: vật lý\n-transfer mechanical impedance"
      }
    ]
  },
  {
    "word": "trở kháng động tự do",
    "definitions": [
      {
        "dict_name": "SPDict",
        "dict_definition": "@Chuyên ngành kỹ thuật\n@Lĩnh vực: toán & tin\n-free motional impedance"
      }
    ]
  },
  {
    "word": "trở kháng thủy lực",
    "definitions": [
      {
        "dict_name": "SPDict",
        "dict_definition": "@Chuyên ngành kỹ thuật\n@Lĩnh vực: điện lạnh\n-hydraulic resistance"
      }
    ]
  },
  {
    "word": "trở kháng sóng hình sin",
    "definitions": [
      {
        "dict_name": "SPDict",
        "dict_definition": "@Chuyên ngành kỹ thuật\n@Lĩnh vực: điện lạnh\n-sine-wave impedance"
      }
    ]
  },
  {
    "word": "trở lui",
    "definitions": [
      {
        "dict_name": "Từ điển Tiếng Việt - Hồ Ngọc Đức",
        "dict_definition": "@trở lui\n- Tính từ đó về thời gian trước: Trở lui lại mười năm xưa."
      },
      {
        "dict_name": "SPDict",
        "dict_definition": "@trở lui [trở lui]\n-to retire;  to withdraw;  to retreat"
      },
      {
        "dict_name": "VNEDICT",
        "dict_definition": "to retire, withdraw, retreat"
      }
    ]
  },
  {
    "word": "trở thành vô nghĩa",
    "definitions": [
      {
        "dict_name": "VNEDICT",
        "dict_definition": "to become meaningless"
      }
    ]
  },
  {
    "word": "trở kháng thích ứng",
    "definitions": [
      {
        "dict_name": "SPDict",
        "dict_definition": "@Chuyên ngành kỹ thuật\n@Lĩnh vực: điện lạnh\n-matched impedance\n@Lĩnh vực: điện tử & viễn thông\n-matching impedance"
      }
    ]
  },
  {
    "word": "trở kháng của mạng điện",
    "definitions": [
      {
        "dict_name": "SPDict",
        "dict_definition": "@Chuyên ngành kỹ thuật\n@Lĩnh vực: điện lạnh\n-network impedance"
      }
    ]
  },
  {
    "word": "trở lực thủy lực",
    "definitions": [
      {
        "dict_name": "SPDict",
        "dict_definition": "@Chuyên ngành kỹ thuật\n@Lĩnh vực: điện lạnh\n-hydraulic resistance"
      }
    ]
  },
  {
    "word": "trở kháng được phối hợp",
    "definitions": [
      {
        "dict_name": "SPDict",
        "dict_definition": "@Chuyên ngành kỹ thuật\n@Lĩnh vực: điện\n-matched impedance"
      }
    ]
  },
  {
    "word": "trở ẩm",
    "definitions": [
      {
        "dict_name": "SPDict",
        "dict_definition": "@Chuyên ngành kỹ thuật\n@Lĩnh vực: điện lạnh\n-moisture resistance"
      }
    ]
  },
  {
    "word": "trở kháng phù hợp",
    "definitions": [
      {
        "dict_name": "SPDict",
        "dict_definition": "@Chuyên ngành kỹ thuật\n@Lĩnh vực: toán & tin\n-matching impedance"
      }
    ]
  },
  {
    "word": "trở và nhấn",
    "definitions": [
      {
        "dict_name": "SPDict",
        "dict_definition": "@Chuyên ngành kỹ thuật\n@Lĩnh vực: toán & tin\n-point and click"
      }
    ]
  },
  {
    "word": "trở kháng mặt đất",
    "definitions": [
      {
        "dict_name": "SPDict",
        "dict_definition": "@Chuyên ngành kỹ thuật\n@Lĩnh vực: điện lạnh\n-ground impedance"
      }
    ]
  },
  {
    "word": "trở ngại thành công",
    "definitions": [
      {
        "dict_name": "SPDict",
        "dict_definition": "@Chuyên ngành kinh tế\n-barriers to success"
      }
    ]
  },
  {
    "word": "trở ngại không nhỏ",
    "definitions": [
      {
        "dict_name": "VNEDICT",
        "dict_definition": "no small obstacle"
      }
    ]
  },
  {
    "word": "trở kháng hỗ cảm",
    "definitions": [
      {
        "dict_name": "SPDict",
        "dict_definition": "@Chuyên ngành kỹ thuật\n@Lĩnh vực: điện lạnh\n-mutual impedance"
      }
    ]
  },
  {
    "word": "trở ngại thuế khóa",
    "definitions": [
      {
        "dict_name": "SPDict",
        "dict_definition": "@Chuyên ngành kinh tế\n-tax disincentive"
      }
    ]
  },
  {
    "word": "trở thành",
    "definitions": [
      {
        "dict_name": "Từ điển Tiếng Việt thông dụng",
        "dict_definition": "thành ra là\nVí dụ:\n- hai người đã trở thành đôi bạn thân"
      },
      {
        "dict_name": "Từ điển Tiếng Việt - Hồ Ngọc Đức",
        "dict_definition": "@trở thành\n- Nh. Trở nên."
      },
      {
        "dict_name": "SPDict",
        "dict_definition": "@trở thành [trở thành]\n-to become\n@Chuyên ngành kỹ thuật\n@Lĩnh vực: hóa học & vật liệu\n-get\n@Lĩnh vực: toán & tin\n-turn"
      },
      {
        "dict_name": "VNEDICT",
        "dict_definition": "to become, grow"
      }
    ]
  },
  {
    "word": "trở về số không",
    "definitions": [
      {
        "dict_name": "SPDict",
        "dict_definition": "@Chuyên ngành kỹ thuật\n@Lĩnh vực: toán & tin\n-return to zero"
      }
    ]
  },
  {
    "word": "trở kháng được tải",
    "definitions": [
      {
        "dict_name": "SPDict",
        "dict_definition": "@Chuyên ngành kỹ thuật\n@Lĩnh vực: toán & tin\n-loaded motional impedance"
      }
    ]
  },
  {
    "word": "trở nạp",
    "definitions": [
      {
        "dict_name": "SPDict",
        "dict_definition": "@Chuyên ngành kỹ thuật\n@Lĩnh vực: điện lạnh\n-immittance"
      }
    ]
  },
  {
    "word": "trở kháng động",
    "definitions": [
      {
        "dict_name": "SPDict",
        "dict_definition": "@Chuyên ngành kỹ thuật\n@Lĩnh vực: toán & tin\n-motional impedance\n@Lĩnh vực: điện lạnh\n-rejecter impedance"
      }
    ]
  },
  {
    "word": "trở kháng (đối với quá trình) truyền âm",
    "definitions": [
      {
        "dict_name": "SPDict",
        "dict_definition": "@Chuyên ngành kỹ thuật\n@Lĩnh vực: vật lý\n-transfer acoustics impedance"
      }
    ]
  },
  {
    "word": "trở kháng đường dây",
    "definitions": [
      {
        "dict_name": "SPDict",
        "dict_definition": "@Chuyên ngành kỹ thuật\n@Lĩnh vực: điện tử & viễn thông\n-line impedance"
      }
    ]
  },
  {
    "word": "trở kháng chuẩn hóa",
    "definitions": [
      {
        "dict_name": "SPDict",
        "dict_definition": "@Chuyên ngành kỹ thuật\n@Lĩnh vực: điện lạnh\n-normalized impedance"
      }
    ]
  },
  {
    "word": "trở kháng âm (thanh)",
    "definitions": [
      {
        "dict_name": "SPDict",
        "dict_definition": "@Chuyên ngành kỹ thuật\n@Lĩnh vực: toán & tin\n-acoustical impedance"
      }
    ]
  },
  {
    "word": "trở ra",
    "definitions": [
      {
        "dict_name": "VNEDICT",
        "dict_definition": "to return (back out of)"
      }
    ]
  },
  {
    "word": "trở kháng điểm dừng",
    "definitions": [
      {
        "dict_name": "SPDict",
        "dict_definition": "@Chuyên ngành kỹ thuật\n@Lĩnh vực: toán & tin\n-stop impedance"
      }
    ]
  },
  {
    "word": "trở kháng truyền âm",
    "definitions": [
      {
        "dict_name": "SPDict",
        "dict_definition": "@Chuyên ngành kỹ thuật\n@Lĩnh vực: điện lạnh\n-transfer acoustic impedance"
      }
    ]
  },
  {
    "word": "trở nên chua",
    "definitions": [
      {
        "dict_name": "SPDict",
        "dict_definition": "@Chuyên ngành kinh tế\n-clabber"
      }
    ]
  },
  {
    "word": "trở mùi",
    "definitions": [
      {
        "dict_name": "Từ điển Tiếng Việt - Hồ Ngọc Đức",
        "dict_definition": "@trở mùi\n- Bắt đầu có mùi thối: Nước mắm trở mùi."
      },
      {
        "dict_name": "SPDict",
        "dict_definition": "@trở mùi [trở mùi]\n-to smell strong/nasty/rancid;   to smell\n@Chuyên ngành kinh tế\n-rancidify\n@Chuyên ngành kỹ thuật\n@Lĩnh vực: hóa học & vật liệu\n-rancid"
      },
      {
        "dict_name": "VNEDICT",
        "dict_definition": "to smell strong or nasty or rancid, smell"
      }
    ]
  },
  {
    "word": "trở kháng song song",
    "definitions": [
      {
        "dict_name": "SPDict",
        "dict_definition": "@Chuyên ngành kỹ thuật\n@Lĩnh vực: điện lạnh\n-parallel impedance"
      }
    ]
  },
  {
    "word": "trở kháng loại bỏ",
    "definitions": [
      {
        "dict_name": "SPDict",
        "dict_definition": "@Chuyên ngành kỹ thuật\n@Lĩnh vực: điện lạnh\n-dynamic impedance\n-rejecter impedance"
      }
    ]
  },
  {
    "word": "trở nên thân thiết",
    "definitions": [
      {
        "dict_name": "VNEDICT",
        "dict_definition": "to become friends"
      }
    ]
  },
  {
    "word": "trở lực bề mặt (nước) đá",
    "definitions": [
      {
        "dict_name": "SPDict",
        "dict_definition": "@Chuyên ngành kỹ thuật\n@Lĩnh vực: điện lạnh\n-ice surface resistance"
      }
    ]
  },
  {
    "word": "trở kháng chuyển tiếp",
    "definitions": [
      {
        "dict_name": "SPDict",
        "dict_definition": "@Chuyên ngành kỹ thuật\n@Lĩnh vực: điện\n-transition impedance"
      }
    ]
  },
  {
    "word": "trở lại trạng thái định vị",
    "definitions": [
      {
        "dict_name": "SPDict",
        "dict_definition": "@Chuyên ngành kỹ thuật\n@Lĩnh vực: giao thông & vận tải\n-reset to normal\n-return to normal"
      }
    ]
  },
  {
    "word": "trở tay",
    "definitions": [
      {
        "dict_name": "Từ điển Tiếng Việt thông dụng",
        "dict_definition": "đối phó ngay trước tình huống bất ngờ\nVí dụ:\n- tôi trở tay không kịp"
      },
      {
        "dict_name": "SPDict",
        "dict_definition": "@trở tay [trở tay]\n-to respond to emergency\n-to turn one\"s hand"
      }
    ]
  },
  {
    "word": "trở lên lầu",
    "definitions": [
      {
        "dict_name": "VNEDICT",
        "dict_definition": "to go back upstairs"
      }
    ]
  },
  {
    "word": "trở kháng âm thanh riêng",
    "definitions": [
      {
        "dict_name": "SPDict",
        "dict_definition": "@Chuyên ngành kỹ thuật\n@Lĩnh vực: điện lạnh\n-specific acoustic impedance"
      }
    ]
  },
  {
    "word": "trở lại cái vấn đề này",
    "definitions": [
      {
        "dict_name": "VNEDICT",
        "dict_definition": "coming back to this issue"
      }
    ]
  },
  {
    "word": "trở kháng mạch vòng",
    "definitions": [
      {
        "dict_name": "SPDict",
        "dict_definition": "@Chuyên ngành kỹ thuật\n@Lĩnh vực: điện lạnh\n-mesh impedance\n-self-impedance"
      }
    ]
  },
  {
    "word": "trở lực của màng không khí",
    "definitions": [
      {
        "dict_name": "SPDict",
        "dict_definition": "@Chuyên ngành kỹ thuật\n@Lĩnh vực: điện lạnh\n-air film resistance"
      }
    ]
  },
  {
    "word": "trở kháng cơ",
    "definitions": [
      {
        "dict_name": "SPDict",
        "dict_definition": "@Chuyên ngành kỹ thuật\n@Lĩnh vực: toán & tin\n-mechanical impedance"
      }
    ]
  },
  {
    "word": "trở kháng bộ lọc",
    "definitions": [
      {
        "dict_name": "SPDict",
        "dict_definition": "@Chuyên ngành kỹ thuật\n@Lĩnh vực: điện tử & viễn thông\n-filter impedance"
      }
    ]
  },
  {
    "word": "trở kháng chân không đặc trưng",
    "definitions": [
      {
        "dict_name": "SPDict",
        "dict_definition": "@Chuyên ngành kỹ thuật\n@Lĩnh vực: vật lý\n-characteristic vacuum impedance\n-impedance of free space"
      }
    ]
  },
  {
    "word": "trở kháng nội",
    "definitions": [
      {
        "dict_name": "SPDict",
        "dict_definition": "@Chuyên ngành kỹ thuật\n@Lĩnh vực: điện lạnh\n-internal impedance"
      }
    ]
  },
  {
    "word": "trở ngại",
    "definitions": [
      {
        "dict_name": "Từ điển Tiếng Việt thông dụng",
        "dict_definition": "cái gây khó khăn, làm cản trở\nVí dụ:\n- trở ngại về vốn \n - gặp trở ngại lớn \n - vượt qua mọi trở ngại"
      },
      {
        "dict_name": "Từ điển Tiếng Việt thông dụng",
        "dict_definition": "cản trở, làm cho không tiến hành được dễ dàng, suôn sẻ\nVí dụ:\n- công việc suôn sẻ, không có gì trở ngại"
      },
      {
        "dict_name": "Từ điển Tiếng Việt - Hồ Ngọc Đức",
        "dict_definition": "@trở ngại\n- d. Cái gây khó khăn, làm cản trở. Công việc gặp nhiều trở ngại. Gây trở ngại cho việc thực hiện kế hoạch."
      },
      {
        "dict_name": "SPDict",
        "dict_definition": "@trở ngại\n*noun\n-hindrance, obstacle, obstruction*verb\n-to hinder, to obstruct\n@Chuyên ngành kinh tế\n-set-back\n@Chuyên ngành kỹ thuật\n-bar\n-constrained\n-hinder\n-hitch\n-incumbrance\n-obstacle\n-obstruction"
      },
      {
        "dict_name": "Việt Anh - Hồ Ngọc Đức",
        "dict_definition": "@trở ngại\n* noun\n- hindrance, obstacle, obstruction\n* verb\n- to hinder, to obstruct"
      },
      {
        "dict_name": "VNEDICT",
        "dict_definition": "hindrance, obstacle, obstruction; to hinder, obstruct"
      }
    ]
  },
  {
    "word": "trở thành sự thật",
    "definitions": [
      {
        "dict_name": "VNEDICT",
        "dict_definition": "to become reality"
      }
    ]
  },
  {
    "word": "trở kháng ma sát",
    "definitions": [
      {
        "dict_name": "SPDict",
        "dict_definition": "@Chuyên ngành kỹ thuật\n@Lĩnh vực: điện lạnh\n-frictional resistance"
      }
    ]
  },
  {
    "word": "trở lại như trước",
    "definitions": [
      {
        "dict_name": "SPDict",
        "dict_definition": "@Chuyên ngành kinh tế\n-recover\n-reviver"
      }
    ]
  },
  {
    "word": "trở về",
    "definitions": [
      {
        "dict_name": "Từ điển Tiếng Việt - Hồ Ngọc Đức",
        "dict_definition": "@trở về\n- đgt. Quay lại chỗ cũ, nơi ở cũ: trở về quê hương."
      },
      {
        "dict_name": "SPDict",
        "dict_definition": "@trở về\n*verb\n-to come back, to be back\n@Chuyên ngành kinh tế\n-ret\n-return\n@Chuyên ngành kỹ thuật\n-calling back\n-carriage return\n-carriage return (CR)\n-comeback\n-reinstatement\n-relapse\n-reoccurrence\n-return\n-return (from a procedure)\n-return (LF+CR)\n-to give back\n-to go back\n-to return"
      },
      {
        "dict_name": "Việt Anh - Hồ Ngọc Đức",
        "dict_definition": "@trở về\n* verb\n- to come back, to be back"
      },
      {
        "dict_name": "VNEDICT",
        "dict_definition": "to come back, be back, return"
      }
    ]
  },
  {
    "word": "trở về sau",
    "definitions": [
      {
        "dict_name": "VNEDICT",
        "dict_definition": "onwards, from then on"
      }
    ]
  },
  {
    "word": "trở kháng trong",
    "definitions": [
      {
        "dict_name": "SPDict",
        "dict_definition": "@Chuyên ngành kỹ thuật\n@Lĩnh vực: điện lạnh\n-internal impedance"
      }
    ]
  },
  {
    "word": "trở kháng mạch hở",
    "definitions": [
      {
        "dict_name": "SPDict",
        "dict_definition": "@Chuyên ngành kỹ thuật\n@Lĩnh vực: điện\n-blocked impedance"
      }
    ]
  },
  {
    "word": "trở về ám ảnh",
    "definitions": [
      {
        "dict_name": "VNEDICT",
        "dict_definition": "to come back to haunt (sb)"
      }
    ]
  },
  {
    "word": "trở chứng",
    "definitions": [
      {
        "dict_name": "Từ điển Tiếng Việt thông dụng",
        "dict_definition": "bỗng nhiên sinh ra tật xấu hoặc thay đổi trạng thái theo chiều hướng xấu\nVí dụ:\n- đang đi tự nhiên xe trở chứng, chết máy"
      },
      {
        "dict_name": "Từ điển Tiếng Việt - Hồ Ngọc Đức",
        "dict_definition": "@trở chứng\n- X. Giở chứng."
      },
      {
        "dict_name": "SPDict",
        "dict_definition": "@trở chứng [trở chứng]\n-như"
      }
    ]
  },
  {
    "word": "trở về đầu băng",
    "definitions": [
      {
        "dict_name": "SPDict",
        "dict_definition": "@Chuyên ngành kỹ thuật\n@Lĩnh vực: toán & tin\n-rewind"
      }
    ]
  },
  {
    "word": "trở kháng sóng sin",
    "definitions": [
      {
        "dict_name": "SPDict",
        "dict_definition": "@Chuyên ngành kỹ thuật\n@Lĩnh vực: điện\n-sine-wave impedance"
      }
    ]
  },
  {
    "word": "trở nên có tác dụng",
    "definitions": [
      {
        "dict_name": "SPDict",
        "dict_definition": "@Chuyên ngành kỹ thuật\n@Lĩnh vực: cơ khí & công trình\n-become effective"
      }
    ]
  },
  {
    "word": "trở kháng mắt lưới",
    "definitions": [
      {
        "dict_name": "SPDict",
        "dict_definition": "@Chuyên ngành kỹ thuật\n@Lĩnh vực: điện lạnh\n-mesh impedance\n-self-impedance"
      }
    ]
  }
]